{"nodes": [{"id": "c_users_artem_riderprojects_karpikengine_first_parties_karpik_jobs_karpik_jobs_jobhandlemethodbuilder_cs", "label": "JobHandleMethodBuilder.cs", "file_type": "code", "source_file": "first-parties/Karpik.Jobs/Karpik.Jobs/JobHandleMethodBuilder.cs", "source_location": "L1"}, {"id": "karpik_jobs_jobhandlemethodbuilder_create", "label": "Create()", "file_type": "code", "source_file": "first-parties/Karpik.Jobs/Karpik.Jobs/JobHandleMethodBuilder.cs", "source_location": "L11"}, {"id": "jobhandlemethodbuilder", "label": "JobHandleMethodBuilder", "file_type": "code", "source_file": "first-parties/Karpik.Jobs/Karpik.Jobs/JobHandleMethodBuilder.cs", "source_location": "L11"}, {"id": "karpik_jobs_jobhandlemethodbuilder_start", "label": "Start()", "file_type": "code", "source_file": "first-parties/Karpik.Jobs/Karpik.Jobs/JobHandleMethodBuilder.cs", "source_location": "L30"}, {"id": "tstatemachine", "label": "TStateMachine", "file_type": "code", "source_file": "first-parties/Karpik.Jobs/Karpik.Jobs/JobHandleMethodBuilder.cs", "source_location": "L30"}, {"id": "karpik_jobs_jobhandlemethodbuilder_setresult", "label": "SetResult()", "file_type": "code", "source_file": "first-parties/Karpik.Jobs/Karpik.Jobs/JobHandleMethodBuilder.cs", "source_location": "L36"}, {"id": "karpik_jobs_jobhandlemethodbuilder_setexception", "label": "SetException()", "file_type": "code", "source_file": "first-parties/Karpik.Jobs/Karpik.Jobs/JobHandleMethodBuilder.cs", "source_location": "L48"}, {"id": "exception", "label": "Exception", "file_type": "code", "source_file": "first-parties/Karpik.Jobs/Karpik.Jobs/JobHandleMethodBuilder.cs", "source_location": "L48"}, {"id": "karpik_jobs_jobhandlemethodbuilder_awaitoncompleted", "label": "AwaitOnCompleted()", "file_type": "code", "source_file": "first-parties/Karpik.Jobs/Karpik.Jobs/JobHandleMethodBuilder.cs", "source_location": "L61"}, {"id": "tawaiter", "label": "TAwaiter", "file_type": "code", "source_file": "first-parties/Karpik.Jobs/Karpik.Jobs/JobHandleMethodBuilder.cs", "source_location": "L61"}, {"id": "karpik_jobs_jobhandlemethodbuilder_awaitunsafeoncompleted", "label": "AwaitUnsafeOnCompleted()", "file_type": "code", "source_file": "first-parties/Karpik.Jobs/Karpik.Jobs/JobHandleMethodBuilder.cs", "source_location": "L69"}, {"id": "karpik_jobs_jobhandlemethodbuilder_setstatemachine", "label": "SetStateMachine()", "file_type": "code", "source_file": "first-parties/Karpik.Jobs/Karpik.Jobs/JobHandleMethodBuilder.cs", "source_location": "L77"}, {"id": "iasyncstatemachine", "label": "IAsyncStateMachine", "file_type": "code", "source_file": "first-parties/Karpik.Jobs/Karpik.Jobs/JobHandleMethodBuilder.cs", "source_location": "L77"}, {"id": "t", "label": "T", "file_type": "code", "source_file": "first-parties/Karpik.Jobs/Karpik.Jobs/JobHandleMethodBuilder.cs", "source_location": "L89"}], "edges": [{"source": "c_users_artem_riderprojects_karpikengine_first_parties_karpik_jobs_karpik_jobs_jobhandlemethodbuilder_cs", "target": "compilerservices", "relation": "imports", "context": "import", "confidence": "EXTRACTED", "source_file": "first-parties/Karpik.Jobs/Karpik.Jobs/JobHandleMethodBuilder.cs", "source_location": "L1", "weight": 1.0}, {"source": "c_users_artem_riderprojects_karpikengine_first_parties_karpik_jobs_karpik_jobs_jobhandlemethodbuilder_cs", "target": "karpik_jobs_jobhandlemethodbuilder_create", "relation": "contains", "confidence": "EXTRACTED", "source_file": "first-parties/Karpik.Jobs/Karpik.Jobs/JobHandleMethodBuilder.cs", "source_location": "L11", "weight": 1.0}, {"source": "karpik_jobs_jobhandlemethodbuilder_create", "target": "jobhandlemethodbuilder", "relation": "references", "confidence": "EXTRACTED", "source_file": "first-parties/Karpik.Jobs/Karpik.Jobs/JobHandleMethodBuilder.cs", "source_location": "L11", "weight": 1.0, "context": "return_type"}, {"source": "c_users_artem_riderprojects_karpikengine_first_parties_karpik_jobs_karpik_jobs_jobhandlemethodbuilder_cs", "target": "karpik_jobs_jobhandlemethodbuilder_start", "relation": "contains", "confidence": "EXTRACTED", "source_file": "first-parties/Karpik.Jobs/Karpik.Jobs/JobHandleMethodBuilder.cs", "source_location": "L30", "weight": 1.0}, {"source": "karpik_jobs_jobhandlemethodbuilder_start", "target": "tstatemachine", "relation": "references", "confidence": "EXTRACTED", "source_file": "first-parties/Karpik.Jobs/Karpik.Jobs/JobHandleMethodBuilder.cs", "source_location": "L30", "weight": 1.0, "context": "parameter_type"}, {"source": "c_users_artem_riderprojects_karpikengine_first_parties_karpik_jobs_karpik_jobs_jobhandlemethodbuilder_cs", "target": "karpik_jobs_jobhandlemethodbuilder_setresult", "relation": "contains", "confidence": "EXTRACTED", "source_file": "first-parties/Karpik.Jobs/Karpik.Jobs/JobHandleMethodBuilder.cs", "source_location": "L36", "weight": 1.0}, {"source": "c_users_artem_riderprojects_karpikengine_first_parties_karpik_jobs_karpik_jobs_jobhandlemethodbuilder_cs", "target": "karpik_jobs_jobhandlemethodbuilder_setexception", "relation": "contains", "confidence": "EXTRACTED", "source_file": "first-parties/Karpik.Jobs/Karpik.Jobs/JobHandleMethodBuilder.cs", "source_location": "L48", "weight": 1.0}, {"source": "karpik_jobs_jobhandlemethodbuilder_setexception", "target": "exception", "relation": "references", "confidence": "EXTRACTED", "source_file": "first-parties/Karpik.Jobs/Karpik.Jobs/JobHandleMethodBuilder.cs", "source_location": "L48", "weight": 1.0, "context": "parameter_type"}, {"source": "c_users_artem_riderprojects_karpikengine_first_parties_karpik_jobs_karpik_jobs_jobhandlemethodbuilder_cs", "target": "karpik_jobs_jobhandlemethodbuilder_awaitoncompleted", "relation": "contains", "confidence": "EXTRACTED", "source_file": "first-parties/Karpik.Jobs/Karpik.Jobs/JobHandleMethodBuilder.cs", "source_location": "L61", "weight": 1.0}, {"source": "karpik_jobs_jobhandlemethodbuilder_awaitoncompleted", "target": "tawaiter", "relation": "references", "confidence": "EXTRACTED", "source_file": "first-parties/Karpik.Jobs/Karpik.Jobs/JobHandleMethodBuilder.cs", "source_location": "L61", "weight": 1.0, "context": "parameter_type"}, {"source": "karpik_jobs_jobhandlemethodbuilder_awaitoncompleted", "target": "tstatemachine", "relation": "references", "confidence": "EXTRACTED", "source_file": "first-parties/Karpik.Jobs/Karpik.Jobs/JobHandleMethodBuilder.cs", "source_location": "L61", "weight": 1.0, "context": "parameter_type"}, {"source": "c_users_artem_riderprojects_karpikengine_first_parties_karpik_jobs_karpik_jobs_jobhandlemethodbuilder_cs", "target": "karpik_jobs_jobhandlemethodbuilder_awaitunsafeoncompleted", "relation": "contains", "confidence": "EXTRACTED", "source_file": "first-parties/Karpik.Jobs/Karpik.Jobs/JobHandleMethodBuilder.cs", "source_location": "L69", "weight": 1.0}, {"source": "karpik_jobs_jobhandlemethodbuilder_awaitunsafeoncompleted", "target": "tawaiter", "relation": "references", "confidence": "EXTRACTED", "source_file": "first-parties/Karpik.Jobs/Karpik.Jobs/JobHandleMethodBuilder.cs", "source_location": "L69", "weight": 1.0, "context": "parameter_type"}, {"source": "karpik_jobs_jobhandlemethodbuilder_awaitunsafeoncompleted", "target": "tstatemachine", "relation": "references", "confidence": "EXTRACTED", "source_file": "first-parties/Karpik.Jobs/Karpik.Jobs/JobHandleMethodBuilder.cs", "source_location": "L69", "weight": 1.0, "context": "parameter_type"}, {"source": "c_users_artem_riderprojects_karpikengine_first_parties_karpik_jobs_karpik_jobs_jobhandlemethodbuilder_cs", "target": "karpik_jobs_jobhandlemethodbuilder_setstatemachine", "relation": "contains", "confidence": "EXTRACTED", "source_file": "first-parties/Karpik.Jobs/Karpik.Jobs/JobHandleMethodBuilder.cs", "source_location": "L77", "weight": 1.0}, {"source": "karpik_jobs_jobhandlemethodbuilder_setstatemachine", "target": "iasyncstatemachine", "relation": "references", "confidence": "EXTRACTED", "source_file": "first-parties/Karpik.Jobs/Karpik.Jobs/JobHandleMethodBuilder.cs", "source_location": "L77", "weight": 1.0, "context": "parameter_type"}, {"source": "c_users_artem_riderprojects_karpikengine_first_parties_karpik_jobs_karpik_jobs_jobhandlemethodbuilder_cs", "target": "karpik_jobs_jobhandlemethodbuilder_create", "relation": "contains", "confidence": "EXTRACTED", "source_file": "first-parties/Karpik.Jobs/Karpik.Jobs/JobHandleMethodBuilder.cs", "source_location": "L89", "weight": 1.0}, {"source": "karpik_jobs_jobhandlemethodbuilder_create", "target": "jobhandlemethodbuilder", "relation": "references", "confidence": "EXTRACTED", "source_file": "first-parties/Karpik.Jobs/Karpik.Jobs/JobHandleMethodBuilder.cs", "source_location": "L89", "weight": 1.0, "context": "return_type"}, {"source": "karpik_jobs_jobhandlemethodbuilder_create", "target": "t", "relation": "references", "confidence": "EXTRACTED", "source_file": "first-parties/Karpik.Jobs/Karpik.Jobs/JobHandleMethodBuilder.cs", "source_location": "L89", "weight": 1.0, "context": "generic_arg"}, {"source": "c_users_artem_riderprojects_karpikengine_first_parties_karpik_jobs_karpik_jobs_jobhandlemethodbuilder_cs", "target": "karpik_jobs_jobhandlemethodbuilder_start", "relation": "contains", "confidence": "EXTRACTED", "source_file": "first-parties/Karpik.Jobs/Karpik.Jobs/JobHandleMethodBuilder.cs", "source_location": "L105", "weight": 1.0}, {"source": "karpik_jobs_jobhandlemethodbuilder_start", "target": "tstatemachine", "relation": "references", "confidence": "EXTRACTED", "source_file": "first-parties/Karpik.Jobs/Karpik.Jobs/JobHandleMethodBuilder.cs", "source_location": "L105", "weight": 1.0, "context": "parameter_type"}, {"source": "c_users_artem_riderprojects_karpikengine_first_parties_karpik_jobs_karpik_jobs_jobhandlemethodbuilder_cs", "target": "karpik_jobs_jobhandlemethodbuilder_setresult", "relation": "contains", "confidence": "EXTRACTED", "source_file": "first-parties/Karpik.Jobs/Karpik.Jobs/JobHandleMethodBuilder.cs", "source_location": "L111", "weight": 1.0}, {"source": "karpik_jobs_jobhandlemethodbuilder_setresult", "target": "t", "relation": "references", "confidence": "EXTRACTED", "source_file": "first-parties/Karpik.Jobs/Karpik.Jobs/JobHandleMethodBuilder.cs", "source_location": "L111", "weight": 1.0, "context": "parameter_type"}, {"source": "c_users_artem_riderprojects_karpikengine_first_parties_karpik_jobs_karpik_jobs_jobhandlemethodbuilder_cs", "target": "karpik_jobs_jobhandlemethodbuilder_setexception", "relation": "contains", "confidence": "EXTRACTED", "source_file": "first-parties/Karpik.Jobs/Karpik.Jobs/JobHandleMethodBuilder.cs", "source_location": "L124", "weight": 1.0}, {"source": "karpik_jobs_jobhandlemethodbuilder_setexception", "target": "exception", "relation": "references", "confidence": "EXTRACTED", "source_file": "first-parties/Karpik.Jobs/Karpik.Jobs/JobHandleMethodBuilder.cs", "source_location": "L124", "weight": 1.0, "context": "parameter_type"}, {"source": "c_users_artem_riderprojects_karpikengine_first_parties_karpik_jobs_karpik_jobs_jobhandlemethodbuilder_cs", "target": "karpik_jobs_jobhandlemethodbuilder_awaitoncompleted", "relation": "contains", "confidence": "EXTRACTED", "source_file": "first-parties/Karpik.Jobs/Karpik.Jobs/JobHandleMethodBuilder.cs", "source_location": "L137", "weight": 1.0}, {"source": "karpik_jobs_jobhandlemethodbuilder_awaitoncompleted", "target": "tawaiter", "relation": "references", "confidence": "EXTRACTED", "source_file": "first-parties/Karpik.Jobs/Karpik.Jobs/JobHandleMethodBuilder.cs", "source_location": "L137", "weight": 1.0, "context": "parameter_type"}, {"source": "karpik_jobs_jobhandlemethodbuilder_awaitoncompleted", "target": "tstatemachine", "relation": "references", "confidence": "EXTRACTED", "source_file": "first-parties/Karpik.Jobs/Karpik.Jobs/JobHandleMethodBuilder.cs", "source_location": "L137", "weight": 1.0, "context": "parameter_type"}, {"source": "c_users_artem_riderprojects_karpikengine_first_parties_karpik_jobs_karpik_jobs_jobhandlemethodbuilder_cs", "target": "karpik_jobs_jobhandlemethodbuilder_awaitunsafeoncompleted", "relation": "contains", "confidence": "EXTRACTED", "source_file": "first-parties/Karpik.Jobs/Karpik.Jobs/JobHandleMethodBuilder.cs", "source_location": "L145", "weight": 1.0}, {"source": "karpik_jobs_jobhandlemethodbuilder_awaitunsafeoncompleted", "target": "tawaiter", "relation": "references", "confidence": "EXTRACTED", "source_file": "first-parties/Karpik.Jobs/Karpik.Jobs/JobHandleMethodBuilder.cs", "source_location": "L145", "weight": 1.0, "context": "parameter_type"}, {"source": "karpik_jobs_jobhandlemethodbuilder_awaitunsafeoncompleted", "target": "tstatemachine", "relation": "references", "confidence": "EXTRACTED", "source_file": "first-parties/Karpik.Jobs/Karpik.Jobs/JobHandleMethodBuilder.cs", "source_location": "L145", "weight": 1.0, "context": "parameter_type"}, {"source": "c_users_artem_riderprojects_karpikengine_first_parties_karpik_jobs_karpik_jobs_jobhandlemethodbuilder_cs", "target": "karpik_jobs_jobhandlemethodbuilder_setstatemachine", "relation": "contains", "confidence": "EXTRACTED", "source_file": "first-parties/Karpik.Jobs/Karpik.Jobs/JobHandleMethodBuilder.cs", "source_location": "L153", "weight": 1.0}, {"source": "karpik_jobs_jobhandlemethodbuilder_setstatemachine", "target": "iasyncstatemachine", "relation": "references", "confidence": "EXTRACTED", "source_file": "first-parties/Karpik.Jobs/Karpik.Jobs/JobHandleMethodBuilder.cs", "source_location": "L153", "weight": 1.0, "context": "parameter_type"}], "raw_calls": [{"caller_nid": "karpik_jobs_jobhandlemethodbuilder_start", "callee": "MoveNext", "is_member_call": true, "source_file": "C:\\Users\\artem\\RiderProjects\\KarpikEngine\\first-parties\\Karpik.Jobs\\Karpik.Jobs\\JobHandleMethodBuilder.cs", "source_location": "L33"}, {"caller_nid": "karpik_jobs_jobhandlemethodbuilder_setresult", "callee": "Signal", "is_member_call": true, "source_file": "C:\\Users\\artem\\RiderProjects\\KarpikEngine\\first-parties\\Karpik.Jobs\\Karpik.Jobs\\JobHandleMethodBuilder.cs", "source_location": "L45"}, {"caller_nid": "karpik_jobs_jobhandlemethodbuilder_setexception", "callee": "Signal", "is_member_call": true, "source_file": "C:\\Users\\artem\\RiderProjects\\KarpikEngine\\first-parties\\Karpik.Jobs\\Karpik.Jobs\\JobHandleMethodBuilder.cs", "source_location": "L58"}, {"caller_nid": "karpik_jobs_jobhandlemethodbuilder_awaitoncompleted", "callee": "OnCompleted", "is_member_call": true, "source_file": "C:\\Users\\artem\\RiderProjects\\KarpikEngine\\first-parties\\Karpik.Jobs\\Karpik.Jobs\\JobHandleMethodBuilder.cs", "source_location": "L66"}, {"caller_nid": "karpik_jobs_jobhandlemethodbuilder_awaitunsafeoncompleted", "callee": "OnCompleted", "is_member_call": true, "source_file": "C:\\Users\\artem\\RiderProjects\\KarpikEngine\\first-parties\\Karpik.Jobs\\Karpik.Jobs\\JobHandleMethodBuilder.cs", "source_location": "L74"}, {"caller_nid": "karpik_jobs_jobhandlemethodbuilder_start", "callee": "MoveNext", "is_member_call": true, "source_file": "C:\\Users\\artem\\RiderProjects\\KarpikEngine\\first-parties\\Karpik.Jobs\\Karpik.Jobs\\JobHandleMethodBuilder.cs", "source_location": "L108"}, {"caller_nid": "karpik_jobs_jobhandlemethodbuilder_setresult", "callee": "Signal", "is_member_call": true, "source_file": "C:\\Users\\artem\\RiderProjects\\KarpikEngine\\first-parties\\Karpik.Jobs\\Karpik.Jobs\\JobHandleMethodBuilder.cs", "source_location": "L121"}, {"caller_nid": "karpik_jobs_jobhandlemethodbuilder_setexception", "callee": "Signal", "is_member_call": true, "source_file": "C:\\Users\\artem\\RiderProjects\\KarpikEngine\\first-parties\\Karpik.Jobs\\Karpik.Jobs\\JobHandleMethodBuilder.cs", "source_location": "L134"}, {"caller_nid": "karpik_jobs_jobhandlemethodbuilder_awaitoncompleted", "callee": "OnCompleted", "is_member_call": true, "source_file": "C:\\Users\\artem\\RiderProjects\\KarpikEngine\\first-parties\\Karpik.Jobs\\Karpik.Jobs\\JobHandleMethodBuilder.cs", "source_location": "L142"}, {"caller_nid": "karpik_jobs_jobhandlemethodbuilder_awaitunsafeoncompleted", "callee": "OnCompleted", "is_member_call": true, "source_file": "C:\\Users\\artem\\RiderProjects\\KarpikEngine\\first-parties\\Karpik.Jobs\\Karpik.Jobs\\JobHandleMethodBuilder.cs", "source_location": "L150"}]}