{"nodes": [{"id": "c_users_artem_riderprojects_karpikengine_modules_shared_tween_tween_core_tween_easings_easing_cs", "label": "Easing.cs", "file_type": "code", "source_file": "Modules/Shared/Tween/Tween.Core/Tween/Easings/Easing.cs", "source_location": "L1"}, {"id": "easings_easing_gtweens_easings", "label": "GTweens.Easings", "file_type": "code", "source_file": "Modules/Shared/Tween/Tween.Core/Tween/Easings/Easing.cs", "source_location": "L1"}], "edges": [{"source": "c_users_artem_riderprojects_karpikengine_modules_shared_tween_tween_core_tween_easings_easing_cs", "target": "easings_easing_gtweens_easings", "relation": "contains", "confidence": "EXTRACTED", "source_file": "Modules/Shared/Tween/Tween.Core/Tween/Easings/Easing.cs", "source_location": "L1", "weight": 1.0}], "raw_calls": []}